kiln_server/__init__.py
kiln_server/custom_errors.py
kiln_server/document_api.py
kiln_server/generate_openapi.py
kiln_server/project_api.py
kiln_server/prompt_api.py
kiln_server/run_api.py
kiln_server/server.py
kiln_server/task_api.py
kiln_server/test_custom_error.py
kiln_server/test_document_api.py
kiln_server/test_project_api.py
kiln_server/test_prompt_api.py
kiln_server/test_run_api.py
kiln_server/test_task_api.py
kiln_server/mcp/README.md
kiln_server/mcp/__init__.py
kiln_server/mcp/mcp.py
kiln_server/mcp/mcp_server_tool_utils.py
kiln_server/mcp/runtime.py
kiln_server/mcp/test_mcp_server.py
kiln_server/mcp/tool_selection.py
kiln_server-0.23.0.dist-info/METADATA
kiln_server-0.23.0.dist-info/WHEEL
kiln_server-0.23.0.dist-info/entry_points.txt
kiln_server-0.23.0.dist-info/licenses/LICENSE.txt
kiln_server-0.23.0.dist-info/RECORD
