Metadata-Version: 2.4
Name: kiln-server
Version: 0.23.0
Summary: Kiln AI Server
Project-URL: Homepage, https://kiln.tech
Project-URL: Repository, https://github.com/Kiln-AI/kiln
Project-URL: Documentation, https://github.com/Kiln-AI/kiln#readme
Project-URL: Issues, https://github.com/Kiln-AI/kiln/issues
Author-email: "Steve Cosman, Chesterfield Laboratories Inc" <scosman@users.noreply.github.com>
License: 
License-File: LICENSE.txt
Classifier: Intended Audience :: Developers
Classifier: License :: OSI Approved :: MIT License
Classifier: Programming Language :: Python :: 3.10
Classifier: Programming Language :: Python :: 3.11
Classifier: Programming Language :: Python :: 3.12
Classifier: Programming Language :: Python :: 3.13
Requires-Python: >=3.10
Requires-Dist: fastapi>=0.115.4
Requires-Dist: httpx>=0.27.2
Requires-Dist: kiln-ai>=0.11.1
Requires-Dist: mcp>=1.10.1
Requires-Dist: pydantic>=2.9.2
Requires-Dist: python-dotenv>=1.0.1
Requires-Dist: python-multipart>=0.0.20
Requires-Dist: uvicorn>=0.32.0
